{
  "id": 4586,
  "event": "R61 Training Event",
  "event_id": 117,
  "dcat_id": 203,
  "discipline": "Boulder",
  "status": "active",
  "status_as_of": "2025-11-05 03:12:13 UTC",
  "category": "F17",
  "round": "Final",
  "points_per_boulder_settings": {
    "fall_deduction": 0.1,
    "points_per_low_zone": 5.0,
    "points_per_top": 25.0,
    "points_per_zone": 10.0,
    "use_low_zone": true
  },
  "format": "IFSC: 1 group 2025 (points)",
  "boulder_jam": true,
  "routes": [
    {
      "id": 113328,
      "name": "1",
      "startlist": "/api/v1/routes/113328/startlist"
    },
    {
      "id": 113329,
      "name": "2",
      "startlist": "/api/v1/routes/113329/startlist"
    },
    {
      "id": 113330,
      "name": "3",
      "startlist": "/api/v1/routes/113330/startlist"
    },
    {
      "id": 113331,
      "name": "4",
      "startlist": "/api/v1/routes/113331/startlist"
    },
    {
      "id": 113332,
      "name": "5",
      "startlist": "/api/v1/routes/113332/startlist"
    },
    {
      "id": 113338,
      "name": "6",
      "startlist": "/api/v1/routes/113338/startlist"
    },
    {
      "id": 113339,
      "name": "7",
      "startlist": "/api/v1/routes/113339/startlist"
    },
    {
      "id": 113342,
      "name": "8",
      "startlist": "/api/v1/routes/113342/startlist"
    }
  ],
  "ranking": [
    {
      "athlete_id": 3247,
      "name": "Rexeisen Anna",
      "firstname": "Anna",
      "lastname": "REXEISEN",
      "country": null,
      "flag_url": null,
      "federation_id": null,
      "bib": "101",
      "rank": 1,
      "score": "64.8",
      "ascents": [
        {
          "route_id": 113328,
          "route_name": "1",
          "top": true,
          "top_tries": 1,
          "zone": true,
          "zone_tries": 1,
          "low_zone": true,
          "points": 25.0,
          "low_zone_tries": 1,
          "modified": "2025-11-11 22:15:43 +00:00",
          "status": "confirmed"
        },
        {
          "route_id": 113329,
          "route_name": "2",
          "top": true,
          "top_tries": 1,
          "zone": true,
          "zone_tries": 1,
          "low_zone": true,
          "points": 25.0,
          "low_zone_tries": 1,
          "modified": "2025-11-11 22:16:40 +00:00",
          "status": "confirmed"
        },
        {
          "route_id": 113330,
          "route_name": "3",
          "top": false,
          "top_tries": null,
          "zone": true,
          "zone_tries": 1,
          "low_zone": true,
          "points": 10.0,
          "low_zone_tries": 1,
          "modified": "2025-11-11 22:18:01 +00:00",
          "status": "confirmed"
        },
        {
          "route_id": 113331,
          "route_name": "4",
          "top": false,
          "top_tries": null,
          "zone": false,
          "zone_tries": null,
          "low_zone": true,
          "points": 4.8,
          "low_zone_tries": 3,
          "modified": "2025-11-11 22:18:27 +00:00",
          "status": "active"
        },
        {
          "route_id": 113332,
          "route_name": "5",
          "top": false,
          "top_tries": null,
          "zone": false,
          "zone_tries": null,
          "low_zone": false,
          "points": 0.0,
          "low_zone_tries": null,
          "modified": "2025-11-05 03:12:13 +00:00",
          "status": "pending"
        },
        {
          "route_id": 113338,
          "route_name": "6",
          "top": false,
          "top_tries": null,
          "zone": false,
          "zone_tries": null,
          "low_zone": false,
          "points": 0.0,
          "low_zone_tries": null,
          "modified": "2025-11-05 03:12:13 +00:00",
          "status": "pending"
        },
        {
          "route_id": 113339,
          "route_name": "7",
          "top": false,
          "top_tries": null,
          "zone": false,
          "zone_tries": null,
          "low_zone": false,
          "points": 0.0,
          "low_zone_tries": null,
          "modified": "2025-11-05 03:12:13 +00:00",
          "status": "pending"
        },
        {
          "route_id": 113342,
          "route_name": "8",
          "top": false,
          "top_tries": null,
          "zone": false,
          "zone_tries": null,
          "low_zone": false,
          "points": 0.0,
          "low_zone_tries": null,
          "modified": "2025-11-05 03:12:13 +00:00",
          "status": "pending"
        }
      ],
      "combined_stages": null,
      "active": true,
      "under_appeal": false
    },
    {
      "athlete_id": 5912,
      "name": "KNIGHTS Penny",
      "firstname": "Penny",
      "lastname": "KNIGHTS",
      "country": null,
      "flag_url": null,
      "federation_id": null,
      "bib": "102",
      "rank": 2,
      "score": "44.8",
      "ascents": [
        {
          "route_id": 113328,
          "route_name": "1",
          "top": false,
          "top_tries": null,
          "zone": true,
          "zone_tries": 2,
          "low_zone": true,
          "points": 9.9,
          "low_zone_tries": 1,
          "modified": "2025-11-11 22:15:53 +00:00",
          "status": "confirmed"
        },
        {
          "route_id": 113329,
          "route_name": "2",
          "top": true,
          "top_tries": 1,
          "zone": true,
          "zone_tries": 1,
          "low_zone": true,
          "points": 25.0,
          "low_zone_tries": 1,
          "modified": "2025-11-11 22:17:05 +00:00",
          "status": "confirmed"
        },
        {
          "route_id": 113330,
          "route_name": "3",
          "top": false,
          "top_tries": null,
          "zone": true,
          "zone_tries": 2,
          "low_zone": true,
          "points": 9.9,
          "low_zone_tries": 1,
          "modified": "2025-11-11 22:18:08 +00:00",
          "status": "active"
        },
        {
          "route_id": 113331,
          "route_name": "4",
          "top": false,
          "top_tries": null,
          "zone": false,
          "zone_tries": null,
          "low_zone": false,
          "points": 0.0,
          "low_zone_tries": null,
          "modified": "2025-11-05 03:12:13 +00:00",
          "status": "pending"
        },
        {
          "route_id": 113332,
          "route_name": "5",
          "top": false,
          "top_tries": null,
          "zone": false,
          "zone_tries": null,
          "low_zone": false,
          "points": 0.0,
          "low_zone_tries": null,
          "modified": "2025-11-05 03:12:13 +00:00",
          "status": "pending"
        },
        {
          "route_id": 113338,
          "route_name": "6",
          "top": false,
          "top_tries": null,
          "zone": false,
          "zone_tries": null,
          "low_zone": false,
          "points": 0.0,
          "low_zone_tries": null,
          "modified": "2025-11-05 03:12:13 +00:00",
          "status": "pending"
        },
        {
          "route_id": 113339,
          "route_name": "7",
          "top": false,
          "top_tries": null,
          "zone": false,
          "zone_tries": null,
          "low_zone": false,
          "points": 0.0,
          "low_zone_tries": null,
          "modified": "2025-11-05 03:12:13 +00:00",
          "status": "pending"
        },
        {
          "route_id": 113342,
          "route_name": "8",
          "top": false,
          "top_tries": null,
          "zone": false,
          "zone_tries": null,
          "low_zone": false,
          "points": 0.0,
          "low_zone_tries": null,
          "modified": "2025-11-05 03:12:13 +00:00",
          "status": "pending"
        }
      ],
      "combined_stages": null,
      "active": true,
      "under_appeal": false
    },
    {
      "athlete_id": 8221,
      "name": "WACHTER Olivia",
      "firstname": "Olivia",
      "lastname": "WACHTER",
      "country": null,
      "flag_url": null,
      "federation_id": null,
      "bib": "103",
      "rank": 3,
      "score": "10.0",
      "ascents": [
        {
          "route_id": 113328,
          "route_name": "1",
          "top": false,
          "top_tries": 3,
          "zone": false,
          "zone_tries": 3,
          "low_zone": false,
          "points": 0.0,
          "low_zone_tries": 3,
          "modified": "2025-11-11 22:16:04 +00:00",
          "status": "confirmed"
        },
        {
          "route_id": 113329,
          "route_name": "2",
          "top": false,
          "top_tries": null,
          "zone": true,
          "zone_tries": 1,
          "low_zone": true,
          "points": 10.0,
          "low_zone_tries": 1,
          "modified": "2025-11-11 22:18:38 +00:00",
          "status": "active"
        },
        {
          "route_id": 113330,
          "route_name": "3",
          "top": false,
          "top_tries": null,
          "zone": false,
          "zone_tries": null,
          "low_zone": false,
          "points": 0.0,
          "low_zone_tries": null,
          "modified": "2025-11-11 22:18:17 +00:00",
          "status": "confirmed"
        },
        {
          "route_id": 113331,
          "route_name": "4",
          "top": false,
          "top_tries": null,
          "zone": false,
          "zone_tries": null,
          "low_zone": false,
          "points": 0.0,
          "low_zone_tries": null,
          "modified": "2025-11-05 03:12:13 +00:00",
          "status": "pending"
        },
        {
          "route_id": 113332,
          "route_name": "5",
          "top": false,
          "top_tries": null,
          "zone": false,
          "zone_tries": null,
          "low_zone": false,
          "points": 0.0,
          "low_zone_tries": null,
          "modified": "2025-11-05 03:12:13 +00:00",
          "status": "pending"
        },
        {
          "route_id": 113338,
          "route_name": "6",
          "top": false,
          "top_tries": null,
          "zone": false,
          "zone_tries": null,
          "low_zone": false,
          "points": 0.0,
          "low_zone_tries": null,
          "modified": "2025-11-05 03:12:13 +00:00",
          "status": "pending"
        },
        {
          "route_id": 113339,
          "route_name": "7",
          "top": false,
          "top_tries": null,
          "zone": false,
          "zone_tries": null,
          "low_zone": false,
          "points": 0.0,
          "low_zone_tries": null,
          "modified": "2025-11-05 03:12:13 +00:00",
          "status": "pending"
        },
        {
          "route_id": 113342,
          "route_name": "8",
          "top": false,
          "top_tries": null,
          "zone": false,
          "zone_tries": null,
          "low_zone": false,
          "points": 0.0,
          "low_zone_tries": null,
          "modified": "2025-11-05 03:12:13 +00:00",
          "status": "pending"
        }
      ],
      "combined_stages": null,
      "active": true,
      "under_appeal": false
    },
    {
      "athlete_id": 9828,
      "name": "MCINTOSH Lauren",
      "firstname": "Lauren",
      "lastname": "MCINTOSH",
      "country": null,
      "flag_url": null,
      "federation_id": null,
      "bib": "104",
      "rank": 4,
      "score": "4.8",
      "ascents": [
        {
          "route_id": 113328,
          "route_name": "1",
          "top": false,
          "top_tries": 1,
          "zone": false,
          "zone_tries": 1,
          "low_zone": true,
          "points": 4.8,
          "low_zone_tries": 3,
          "modified": "2025-11-11 22:16:50 +00:00",
          "status": "active"
        },
        {
          "route_id": 113329,
          "route_name": "2",
          "top": false,
          "top_tries": null,
          "zone": false,
          "zone_tries": null,
          "low_zone": false,
          "points": 0.0,
          "low_zone_tries": null,
          "modified": "2025-11-05 03:12:13 +00:00",
          "status": "pending"
        },
        {
          "route_id": 113330,
          "route_name": "3",
          "top": false,
          "top_tries": null,
          "zone": false,
          "zone_tries": null,
          "low_zone": false,
          "points": 0.0,
          "low_zone_tries": null,
          "modified": "2025-11-11 22:18:16 +00:00",
          "status": "confirmed"
        },
        {
          "route_id": 113331,
          "route_name": "4",
          "top": false,
          "top_tries": null,
          "zone": false,
          "zone_tries": null,
          "low_zone": false,
          "points": 0.0,
          "low_zone_tries": null,
          "modified": "2025-11-05 03:12:13 +00:00",
          "status": "pending"
        },
        {
          "route_id": 113332,
          "route_name": "5",
          "top": false,
          "top_tries": null,
          "zone": false,
          "zone_tries": null,
          "low_zone": false,
          "points": 0.0,
          "low_zone_tries": null,
          "modified": "2025-11-05 03:12:13 +00:00",
          "status": "pending"
        },
        {
          "route_id": 113338,
          "route_name": "6",
          "top": false,
          "top_tries": null,
          "zone": false,
          "zone_tries": null,
          "low_zone": false,
          "points": 0.0,
          "low_zone_tries": null,
          "modified": "2025-11-05 03:12:13 +00:00",
          "status": "pending"
        },
        {
          "route_id": 113339,
          "route_name": "7",
          "top": false,
          "top_tries": null,
          "zone": false,
          "zone_tries": null,
          "low_zone": false,
          "points": 0.0,
          "low_zone_tries": null,
          "modified": "2025-11-05 03:12:13 +00:00",
          "status": "pending"
        },
        {
          "route_id": 113342,
          "route_name": "8",
          "top": false,
          "top_tries": null,
          "zone": false,
          "zone_tries": null,
          "low_zone": false,
          "points": 0.0,
          "low_zone_tries": null,
          "modified": "2025-11-05 03:12:13 +00:00",
          "status": "pending"
        }
      ],
      "combined_stages": null,
      "active": true,
      "under_appeal": false
    }
  ],
  "startlist": [
    {
      "athlete_id": 3247,
      "route_start_positions": [],
      "name": "REXEISEN Anna",
      "firstname": "Anna",
      "lastname": "REXEISEN",
      "bib": "101",
      "country": null,
      "flag_url": null,
      "federation_id": null
    },
    {
      "athlete_id": 5912,
      "route_start_positions": [],
      "name": "KNIGHTS Penny",
      "firstname": "Penny",
      "lastname": "KNIGHTS",
      "bib": "102",
      "country": null,
      "flag_url": null,
      "federation_id": null
    },
    {
      "athlete_id": 8221,
      "route_start_positions": [],
      "name": "WACHTER Olivia",
      "firstname": "Olivia",
      "lastname": "WACHTER",
      "bib": "103",
      "country": null,
      "flag_url": null,
      "federation_id": null
    },
    {
      "athlete_id": 9828,
      "route_start_positions": [],
      "name": "MCINTOSH Lauren",
      "firstname": "Lauren",
      "lastname": "MCINTOSH",
      "bib": "104",
      "country": null,
      "flag_url": null,
      "federation_id": null
    }
  ]
}